redis_rate_limiter/__init__.py
redis_rate_limiter/config.py
redis_rate_limiter/exceptions.py
redis_rate_limiter/rate_limiter.py
redis_rate_limiter/redis_client.py
redis_rate_limiter-0.2.0.dist-info/WHEEL
redis_rate_limiter-0.2.0.dist-info/METADATA
redis_rate_limiter-0.2.0.dist-info/RECORD
