Metadata-Version: 2.1
Name: redis-rate-limiter
Version: 0.2.0
Summary: A Redis based rate limiter implementation for Python
Home-page: https://github.com/duyixian1234/redis-rate-limiter
License: MIT
Author: duyixian
Author-email: duyixian1234@qq.com
Requires-Python: >=3.8,<4.0
Classifier: License :: OSI Approved :: MIT License
Classifier: Programming Language :: Python :: 3
Classifier: Programming Language :: Python :: 3.8
Classifier: Programming Language :: Python :: 3.9
Classifier: Programming Language :: Python :: 3.10
Requires-Dist: redis (>=1)
Project-URL: Repository, https://github.com/duyixian1234/redis-rate-limiter
